{
    "variants": {
        "facing=north,open=false": {
            "model": "cobblefurnies:block/drawer/cyan"
        },
        "facing=east,open=false": {
            "model": "cobblefurnies:block/drawer/cyan",
            "y": 90
        },
        "facing=south,open=false": {
            "model": "cobblefurnies:block/drawer/cyan",
            "y": 180
        },
        "facing=west,open=false": {
            "model": "cobblefurnies:block/drawer/cyan",
            "y": 270
        },
        "facing=north,open=true": {
            "model": "cobblefurnies:block/drawer/cyan_open"
        },
        "facing=east,open=true": {
            "model": "cobblefurnies:block/drawer/cyan_open",
            "y": 90
        },
        "facing=south,open=true": {
            "model": "cobblefurnies:block/drawer/cyan_open",
            "y": 180
        },
        "facing=west,open=true": {
            "model": "cobblefurnies:block/drawer/cyan_open",
            "y": 270
        }
    }
}